Metadata-Version: 1.1
Name: thermos-cli
Version: 0.1.0
Summary: A command line program in Python for creating flask standard application structure, blueprints and templates.
Home-page: https://github.com/mwangi-njuguna/thermos-cli
Author: Mwangi Njuguna
Author-email: mwanginjuguna59@gmail.com
License: MIT
Keywords: flask,cli
Platform: UNKNOWN
Classifier: Development Status :: 3 - Alpha
Classifier: Intended Audience :: Developers
Classifier: Topic :: Utilities
Classifier: License :: OSI Approved :: MIT License
Classifier: Natural Language :: English
Classifier: Operating System :: OS Independent
Classifier: Programming Language :: Python :: 2
Classifier: Programming Language :: Python :: 2.6
Classifier: Programming Language :: Python :: 2.7
Classifier: Programming Language :: Python :: 3
Classifier: Programming Language :: Python :: 3.2
Classifier: Programming Language :: Python :: 3.3
Classifier: Programming Language :: Python :: 3.4
Classifier: Programming Language :: Python :: 3.6
